pythoneasy/__init__.py
pythoneasy/api.py
pythoneasy-1.4.dist-info/LICENSE
pythoneasy-1.4.dist-info/METADATA
pythoneasy-1.4.dist-info/WHEEL
pythoneasy-1.4.dist-info/top_level.txt
pythoneasy-1.4.dist-info/RECORD
